odoo/addons/l10n_br_fiscal_subsequent_document/README.rst
odoo/addons/l10n_br_fiscal_subsequent_document/__init__.py
odoo/addons/l10n_br_fiscal_subsequent_document/__manifest__.py
odoo/addons/l10n_br_fiscal_subsequent_document/demo/subsequent_operation_demo.xml
odoo/addons/l10n_br_fiscal_subsequent_document/i18n/l10n_br_fiscal_subsequent_document.pot
odoo/addons/l10n_br_fiscal_subsequent_document/models/__init__.py
odoo/addons/l10n_br_fiscal_subsequent_document/models/document.py
odoo/addons/l10n_br_fiscal_subsequent_document/models/document_mixin.py
odoo/addons/l10n_br_fiscal_subsequent_document/models/operation.py
odoo/addons/l10n_br_fiscal_subsequent_document/models/subsequent_document.py
odoo/addons/l10n_br_fiscal_subsequent_document/models/subsequent_operation.py
odoo/addons/l10n_br_fiscal_subsequent_document/readme/CONTRIBUTORS.md
odoo/addons/l10n_br_fiscal_subsequent_document/readme/DESCRIPTION.md
odoo/addons/l10n_br_fiscal_subsequent_document/security/ir.model.access.csv
odoo/addons/l10n_br_fiscal_subsequent_document/static/description/icon.png
odoo/addons/l10n_br_fiscal_subsequent_document/static/description/index.html
odoo/addons/l10n_br_fiscal_subsequent_document/tests/__init__.py
odoo/addons/l10n_br_fiscal_subsequent_document/tests/test_subsequent_operation.py
odoo/addons/l10n_br_fiscal_subsequent_document/views/document_view.xml
odoo/addons/l10n_br_fiscal_subsequent_document/views/l10n_br_fiscal_action.xml
odoo/addons/l10n_br_fiscal_subsequent_document/views/l10n_br_fiscal_menu.xml
odoo/addons/l10n_br_fiscal_subsequent_document/views/operation_view.xml
odoo/addons/l10n_br_fiscal_subsequent_document/views/subsequent_document_view.xml
odoo/addons/l10n_br_fiscal_subsequent_document/views/subsequent_operation_view.xml
odoo_addon_l10n_br_fiscal_subsequent_document-16.0.2.0.0.dist-info/METADATA
odoo_addon_l10n_br_fiscal_subsequent_document-16.0.2.0.0.dist-info/WHEEL
odoo_addon_l10n_br_fiscal_subsequent_document-16.0.2.0.0.dist-info/top_level.txt
odoo_addon_l10n_br_fiscal_subsequent_document-16.0.2.0.0.dist-info/RECORD
